{
  "name": "|| Ethereal. |",
  "description": "@farnaush\n\n\nThe geometric shapes of modern architecture synthesized to the maximum in an urban kaleidoscope of dark colors. A cold sun illuminates the scene but does not heat up, it does not give warmth but rather numbs the senses. A point of escape with no exit, which forces the viewer to wonder about the prison of the current.\n\nCollection #1 - Drop 5 of 5",
  "image": "https://ipfs.infura.io/ipfs/QmQFcwvK6BkcuJEnbjZxo74P2dfezDQoFm6rCnZS4UErNm",
  "external_url": "https://xdai.unique.one/token2/0xED1eFC6EFCEAAB9F6d609feC89c9E675Bf1efB0a:56",
  "attributes": [],
  "id": "56",
  "editions": "20",
  "price": "47.5",
  "fee": "2.5"
}